picomet/__init__.py
picomet/admin.py
picomet/apps.py
picomet/cli.py
picomet/compiler.py
picomet/consumers.py
picomet/copier.py
picomet/decorators.py
picomet/finders.py
picomet/forms.py
picomet/helpers.py
picomet/http.py
picomet/loaders.py
picomet/middleware.py
picomet/models.py
picomet/parser.py
picomet/shortcuts.py
picomet/sockets.py
picomet/tailwind.js
picomet/tests.py
picomet/transformer.py
picomet/types.py
picomet/urls.py
picomet/utils.py
picomet/views.py
picomet/assets/picomet/comet.js
picomet/assets/picomet/comet.ts
picomet/assets/picomet/hmr.js
picomet/assets/picomet/hmr.ts
picomet/backends/__init__.py
picomet/backends/picomet.py
picomet/management/commands/build.py
picomet/management/commands/newapp.py
picomet/management/commands/recompile.py
picomet/migrations/__init__.py
picomet/template/.env.example.jinja
picomet/template/.env.jinja
picomet/template/.gitignore
picomet/template/copier.yml
picomet/template/manage.py
picomet/template/pyproject.toml.jinja
picomet/template/{% if Deployment == 'Vercel' %}build.sh{% endif %}.jinja
picomet/template/{% if Deployment == 'Vercel' %}vercel.json{% endif %}.jinja
picomet/template/{% if Precommit %}.pre-commit-config.yaml{% endif %}.jinja
picomet/template/{% if Tailwind or Prettier %}package.json{% endif %}.jinja
picomet/template/apps/__init__.py
picomet/template/apps/core/__init__.py
picomet/template/apps/core/actions.py
picomet/template/apps/core/admin.py
picomet/template/apps/core/apps.py
picomet/template/apps/core/forms.py
picomet/template/apps/core/managers.py
picomet/template/apps/core/models.py
picomet/template/apps/core/tests.py
picomet/template/apps/core/urls.py
picomet/template/apps/core/views.py
picomet/template/apps/core/comets/Index.css
picomet/template/apps/core/comets/Index.html
picomet/template/apps/core/comets/components/Arrow.html
picomet/template/comets/Base.html.jinja
picomet/template/comets/{% if Tailwind %}base.postcss.js{% endif %}.jinja
picomet-0.0.42.dist-info/LICENSE
picomet-0.0.42.dist-info/METADATA
picomet-0.0.42.dist-info/WHEEL
picomet-0.0.42.dist-info/entry_points.txt
picomet-0.0.42.dist-info/top_level.txt
picomet-0.0.42.dist-info/RECORD
