Metadata-Version: 2.2
Name: picomet
Version: 0.0.42
Summary: The nextjs of django
Author-email: Al Mahdi <picometproject@gmail.com>
License: MIT
Project-URL: Documentation, https://picomet.readthedocs.io
Project-URL: Source, https://github.com/picomet/picomet
Project-URL: Funding, https://buymeacoffee.com/almahdi404
Keywords: picomet,django,nextjs
Classifier: Environment :: Web Environment
Classifier: Framework :: Django
Classifier: Framework :: Django :: 5.0
Classifier: Framework :: Django :: 5.1
Classifier: Intended Audience :: Developers
Classifier: License :: OSI Approved :: MIT License
Classifier: Programming Language :: Python
Classifier: Programming Language :: Python :: 3.12
Classifier: Programming Language :: Python :: 3.13
Classifier: Operating System :: OS Independent
Classifier: Typing :: Typed
Requires-Python: >=3.12
License-File: LICENSE
Requires-Dist: django>=5.0
Requires-Dist: htmst==1.0a9
